chinese_calendar/__init__.py
chinese_calendar/constants.py
chinese_calendar/utils.py
ChineseCalendarYf-1.2.dist-info/METADATA
ChineseCalendarYf-1.2.dist-info/WHEEL
ChineseCalendarYf-1.2.dist-info/top_level.txt
ChineseCalendarYf-1.2.dist-info/RECORD
