Metadata-Version: 2.1
Name: ChineseCalendarYf
Version: 1.2
Summary: check if some day is holiday or workday in China
Home-page: https://github.com/Zxr1314/ChineseCalendarYf
Author: zxr
Author-email: zxr_seulist@163.com
License: UNKNOWN
Platform: UNKNOWN
